IndertCT_python/__init__.py
IndertCT_python/api_conn.py
IndertCT-0.0.7.dist-info/LICENSE
IndertCT-0.0.7.dist-info/METADATA
IndertCT-0.0.7.dist-info/WHEEL
IndertCT-0.0.7.dist-info/top_level.txt
IndertCT-0.0.7.dist-info/RECORD
