Metadata-Version: 2.1
Name: IndertCT
Version: 0.0.7
Summary: Package for IndertCT´s Api
Author: Dinis Moreira
Author-email: jusupaq@gmail.com
Keywords: python,IndertCT,cryptocurrency,money,market forecast,crypto,crypto market,cryptocurrency market,API,Integration,IndertCT integration
Classifier: Development Status :: 1 - Planning
Classifier: Operating System :: Unix
Classifier: Operating System :: MacOS :: MacOS X
Classifier: Operating System :: Microsoft :: Windows
License-File: LICENSE
Requires-Dist: requests
